optimizingdataanalysisprograms/__init__.py
optimizingdataanalysisprograms/odp.py
optimizing_data_analysis_program-1.0.1.dist-info/METADATA
optimizing_data_analysis_program-1.0.1.dist-info/WHEEL
optimizing_data_analysis_program-1.0.1.dist-info/top_level.txt
optimizing_data_analysis_program-1.0.1.dist-info/RECORD
