Metadata-Version: 2.1
Name: optimizing-data-analysis-program
Version: 1.0.1
Summary: your data analysis
Home-page: https://www.youtube.com/@user-vj5zo5ku9h
Author: rayfine
Author-email: scientist.ops.ray@gmail.com
License: analysis.boys
Platform: UNKNOWN
Requires-Python: >=3
